{
  "name": "database-server",
  "displayName": "MCP Database Server",
  "description": "Comprehensive database server supporting PostgreSQL, MySQL, and SQLite with natural language SQL query capabilities. Enables AI agents to interact with databases through both direct SQL and natural language queries.",
  "author": "Souhardya Kundu",
  "homepage": "https://github.com/Souhar-dya/mcp-db-server",
  "sourceUrl": "https://github.com/Souhar-dya/mcp-db-server",
  "npmPackage": null,
  "pythonPackage": null,
  "dockerImage": "souhardyak/mcp-db-server",
  "capabilities": [
    "database",
    "natural-language",
    "multi-database",
    "query-execution",
    "schema-inspection"
  ],
  "categories": [
    "database",
    "productivity",
    "development"
  ],
  "keywords": [
    "database",
    "sql",
    "postgresql",
    "mysql",
    "sqlite",
    "natural-language",
    "ai-assistant",
    "query-builder"
  ],
  "configuration": {
    "required": [
      "DATABASE_URL"
    ],
    "optional": [
      "DB_HOST",
      "DB_PORT", 
      "DB_USER",
      "DB_PASSWORD",
      "DB_NAME"
    ]
  },
  "tools": [
    {
      "name": "query_database",
      "description": "Execute natural language queries against the database"
    },
    {
      "name": "list_tables", 
      "description": "List all available tables in the database"
    },
    {
      "name": "describe_table",
      "description": "Get detailed schema information for a specific table"
    },
    {
      "name": "execute_sql",
      "description": "Execute raw SQL queries with safety checks"
    },
    {
      "name": "connect_to_database",
      "description": "Connect to a new database with provided credentials"
    },
    {
      "name": "get_connection_examples",
      "description": "Get example connection strings for different database types"
    },
    {
      "name": "get_current_database_info",
      "description": "Get information about the currently connected database"
    }
  ],
  "examples": [
    {
      "name": "SQLite Connection",
      "config": {
        "DATABASE_URL": "sqlite+aiosqlite:///data/mydb.db"
      }
    },
    {
      "name": "PostgreSQL Connection", 
      "config": {
        "DATABASE_URL": "postgresql+asyncpg://user:password@localhost:5432/mydb"
      }
    },
    {
      "name": "MySQL Connection",
      "config": {
        "DATABASE_URL": "mysql+aiomysql://user:password@localhost:3306/mydb"
      }
    }
  ],
  "license": "MIT",
  "version": "1.0.0"
}